imgui.cpython-39-darwin.so
imgui/__init__.pyi
imgui/implot/__init__.pyi
imgui/imnodes/__init__.pyi
imgui/glfw/__init__.pyi
py_imgui_redux-5.0.0.dist-info/RECORD
py_imgui_redux-5.0.0.dist-info/WHEEL
py_imgui_redux-5.0.0.dist-info/top_level.txt
py_imgui_redux-5.0.0.dist-info/METADATA
py_imgui_redux-5.0.0.dist-info/licenses/LICENSE
