Metadata-Version: 2.4
Name: py-imgui-redux
Version: 5.0.0
Summary: A python wrapper for DearImGUI and popular extensions
Author: Alagyn
License-Expression: MIT
Project-URL: Homepage, https://github.com/alagyn/py-imgui-redux
Project-URL: Bug Tracker, https://github.com/alagyn/py-imgui-redux/issues
Classifier: Programming Language :: Python :: 3
Classifier: Operating System :: OS Independent
Classifier: Development Status :: 5 - Production/Stable
Classifier: Intended Audience :: Developers
Classifier: Topic :: Software Development :: Libraries :: Python Modules
Classifier: Topic :: Software Development :: User Interfaces
Requires-Python: >=3.9
License-File: LICENSE
Dynamic: license-file
